LICENSE
MANIFEST.in
README.rst
setup.cfg
setup.py
drf_optionalfields/__init__.py
drf_optionalfields/mixins.py
drf_optionalfields.egg-info/PKG-INFO
drf_optionalfields.egg-info/SOURCES.txt
drf_optionalfields.egg-info/dependency_links.txt
drf_optionalfields.egg-info/requires.txt
drf_optionalfields.egg-info/top_level.txt