Metadata-Version: 1.1
Name: drf-optionalfields
Version: 0.9.14
Summary: Fine tuning for serialized fields
Home-page: https://github.com/sideris/drf-optionalfields
Author: Petros G. Sideris
Author-email: pgsideris@gmail.com
License: MIT
Platform: UNKNOWN
Classifier: Programming Language :: Python :: 2
Classifier: Programming Language :: Python :: 3
Classifier: License :: OSI Approved :: MIT License
Classifier: Topic :: Software Development :: Libraries
Classifier: Intended Audience :: Developers
Classifier: Framework :: Django
